darlog/__init__.py
darlog/py23/__attrs.py
darlog/py23/__dataclass_attrs.py
darlog/py23/__dataclass_fallback.py
darlog/py23/__init__.py
darlog/py23/__py_ver.py
darlog/py23/__str.py
darlog_py23-1.2.1.dist-info/LICENSE.md
darlog_py23-1.2.1.dist-info/METADATA
darlog_py23-1.2.1.dist-info/WHEEL
darlog_py23-1.2.1.dist-info/top_level.txt
darlog_py23-1.2.1.dist-info/RECORD
