Metadata-Version: 2.1
Name: darlog-py23
Version: 1.2.1
Summary: A tiny compatibility module for cross-Python2/3 code.
Home-page: https://github.com/Lex-DRL/darlog-py23
Author: Lex Darlog (Lex-DRL)
Maintainer: Lex Darlog (Lex-DRL)
License: LGPL-3.0-only
Keywords: 2to3,3to2,six,compatibility,wrapper
Classifier: Development Status :: 5 - Production/Stable
Classifier: Intended Audience :: Developers
Classifier: License :: OSI Approved :: GNU Lesser General Public License v3 (LGPLv3)
Classifier: Natural Language :: English
Classifier: Operating System :: OS Independent
Classifier: Programming Language :: Python
Classifier: Programming Language :: Python :: 2
Classifier: Programming Language :: Python :: 2.7
Classifier: Programming Language :: Python :: 3
Classifier: Programming Language :: Python :: 3.7
Classifier: Programming Language :: Python :: 3.8
Classifier: Programming Language :: Python :: 3.9
Classifier: Programming Language :: Python :: 3.10
Classifier: Topic :: Software Development :: Libraries :: Python Modules
Classifier: Typing :: Typed
Requires-Python: !=3.0.*,!=3.1.*,!=3.2.*,!=3.3.*,!=3.4.*,!=3.5.*,!=3.6.*,<4,>=2.7
License-File: LICENSE.md
